executors/__init__.py
executors/hashing.py
executors/pkg.py
prompt_templates/__init__.py
prompt_templates/refine_rules_v1.json
prompt_templates/summarize_v1.json
prompt_templates/triage_v1.json
pypi_init/__init__.py
sys_scan_agent/__init__.py
sys_scan_agent/audit.py
sys_scan_agent/baseline.py
sys_scan_agent/calibration.py
sys_scan_agent/canonicalize.py
sys_scan_agent/cli.py
sys_scan_agent/config.py
sys_scan_agent/correlator.py
sys_scan_agent/counterfactual.py
sys_scan_agent/data_governance.py
sys_scan_agent/db_pool.py
sys_scan_agent/endpoint_classification.py
sys_scan_agent/enricher.py
sys_scan_agent/evaluation.py
sys_scan_agent/graph.py
sys_scan_agent/graph_analysis.py
sys_scan_agent/graph_nodes.py
sys_scan_agent/graph_nodes_enhanced.py
sys_scan_agent/graph_nodes_ui.py
sys_scan_agent/graph_state.py
sys_scan_agent/hf_loader.py
sys_scan_agent/integrity.py
sys_scan_agent/ipc_server.py
sys_scan_agent/knowledge.py
sys_scan_agent/llm.py
sys_scan_agent/llm_cache.py
sys_scan_agent/llm_models.py
sys_scan_agent/llm_provider.py
sys_scan_agent/llm_provider_enhanced.py
sys_scan_agent/loader.py
sys_scan_agent/metrics.py
sys_scan_agent/metrics_exporter.py
sys_scan_agent/metrics_node.py
sys_scan_agent/model_loader.py
sys_scan_agent/performance.py
sys_scan_agent/performance_baseline.py
sys_scan_agent/pipeline.py
sys_scan_agent/rarity_generate.py
sys_scan_agent/redaction.py
sys_scan_agent/reduction.py
sys_scan_agent/report_diff.py
sys_scan_agent/report_html.py
sys_scan_agent/retriever.py
sys_scan_agent/risk.py
sys_scan_agent/rule_gap_miner.py
sys_scan_agent/rule_redundancy.py
sys_scan_agent/rule_refiner.py
sys_scan_agent/rule_suggest.py
sys_scan_agent/rules.py
sys_scan_agent/sandbox.py
sys_scan_agent/tool_wrapper.py
sys_scan_agent/tools.py
sys_scan_agent/tools_enhanced.py
sys_scan_agent/util_hash.py
sys_scan_agent/util_normalization.py
sys_scan_agent/utils.py
sys_scan_agent/graph/__init__.py
sys_scan_agent/graph/analysis.py
sys_scan_agent/graph/base.py
sys_scan_agent-7.0.0.dist-info/licenses/LICENSE
sys_scan_agent-7.0.0.dist-info/METADATA
sys_scan_agent-7.0.0.dist-info/WHEEL
sys_scan_agent-7.0.0.dist-info/entry_points.txt
sys_scan_agent-7.0.0.dist-info/top_level.txt
sys_scan_agent-7.0.0.dist-info/RECORD
