Metadata-Version: 2.4
Name: sys-scan-agent
Version: 7.0.0
Summary: AI-powered intelligence layer for the sys-scan-graph security scanner.
Home-page: https://github.com/J-mazz/sys-scan-graph
Author: Joseph Mazzini
Author-email: Joseph Mazzini <joseph@mazzlabs.works>
Maintainer-email: Joseph Mazzini <joseph@mazzlabs.works>
License: Apache License 2.0
Project-URL: Homepage, https://github.com/J-mazz/sys-scan-graph
Project-URL: Repository, https://github.com/J-mazz/sys-scan-graph
Project-URL: Issues, https://github.com/J-mazz/sys-scan-graph/issues
Project-URL: Documentation, https://github.com/J-mazz/sys-scan-graph#readme
Keywords: security,scanner,ai,intelligence,analysis
Classifier: Programming Language :: Python :: 3
Classifier: License :: OSI Approved :: Apache Software License
Classifier: Operating System :: POSIX :: Linux
Classifier: Topic :: Security
Classifier: Development Status :: 4 - Beta
Classifier: Intended Audience :: System Administrators
Classifier: Topic :: System :: Monitoring
Requires-Python: >=3.8
License-File: LICENSE
Requires-Dist: pydantic<3,>=2.7
Requires-Dist: sqlalchemy<3,>=2.0
Requires-Dist: typer<0.13,>=0.12
Requires-Dist: rich<14,>=13.0
Requires-Dist: click<8.2.0,>=8.1.0
Requires-Dist: pyyaml<7,>=6.0
Requires-Dist: orjson<4,>=3.9
Requires-Dist: jsonschema<5,>=4.21
Requires-Dist: PyNaCl<2,>=1.5
Requires-Dist: huggingface_hub>=0.20.0
Provides-Extra: ai
Requires-Dist: langgraph<1,>=0.2; extra == "ai"
Requires-Dist: langchain-core<1,>=0.3; extra == "ai"
Requires-Dist: torch>=2.0.0; extra == "ai"
Requires-Dist: transformers>=4.40.0; extra == "ai"
Requires-Dist: peft>=0.10.0; extra == "ai"
Requires-Dist: accelerate>=0.29.0; extra == "ai"
Requires-Dist: safetensors>=0.4.0; extra == "ai"
Requires-Dist: llama-cpp-python>=0.2.26; extra == "ai"
Provides-Extra: api
Requires-Dist: langchain<1,>=0.3; extra == "api"
Requires-Dist: langchain-core<1,>=0.3; extra == "api"
Requires-Dist: langchain-openai<1,>=0.2; extra == "api"
Requires-Dist: langchain-anthropic<1,>=0.2; extra == "api"
Provides-Extra: dev
Requires-Dist: pytest<9,>=8.0; extra == "dev"
Requires-Dist: pytest-asyncio<0.24,>=0.23; extra == "dev"
Requires-Dist: black<24,>=23.0; extra == "dev"
Requires-Dist: isort<6,>=5.12; extra == "dev"
Requires-Dist: mypy<2,>=1.5; extra == "dev"
Requires-Dist: flake8<7,>=6.0; extra == "dev"
Dynamic: author
Dynamic: home-page
Dynamic: license-file
Dynamic: requires-python
